{
  "persons": [
    {
      "name": "Bhupen Gupta",
      "number": "7982787199",
      "id": 1
    },
    {
      "name": "Ada Lovelace",
      "number": "39-44-5323523",
      "id": 2
    },
    {
      "name": "Pratyush",
      "number": "9876512340",
      "id": 4
    },
    {
      "name": "Arjun",
      "number": "9876543210",
      "id": 5
    },
    {
      "name": "Mukesh Gupta",
      "number": "9810514602",
      "id": 6
    },
    {
      "name": "Dan Abramov",
      "number": "12-43-234345",
      "id": 7
    }
  ]
}